lidarSuit/__init__.py
lidarSuit/dataAttributesL1.py
lidarSuit/dataOperator.py
lidarSuit/filters.py
lidarSuit/lidar_code.py
lidarSuit/lstConfig.py
lidarSuit/utilities.py
lidarSuit/version.py
lidarSuit/visualization.py
lidarSuit/windPropRetrieval.py
lidarSuit/windPropRetrieval6Beam.py
lidarSuit-0.1.6.dist-info/AUTHORS.rst
lidarSuit-0.1.6.dist-info/LICENSE
lidarSuit-0.1.6.dist-info/METADATA
lidarSuit-0.1.6.dist-info/WHEEL
lidarSuit-0.1.6.dist-info/entry_points.txt
lidarSuit-0.1.6.dist-info/top_level.txt
lidarSuit-0.1.6.dist-info/RECORD
