Metadata-Version: 2.1
Name: lidarSuit
Version: 0.1.6
Summary: LIDAR procedures
Author: José Dias Neto
Author-email: jdiasn@gmail.com
License:         
Project-URL: homepage, https://github.com/jdiasn/lidarSuit
Project-URL: repository, https://github.com/jdiasn/lidarSuit
Project-URL: documentation, https://lidarSuit.readthedocs.io
Keywords: Lidar,Turbulence,Wind
Classifier: Development Status :: 2 - Pre-Alpha
Classifier: Intended Audience :: Science/Research
Classifier: License :: OSI Approved :: BSD License
Classifier: Natural Language :: English
Classifier: Programming Language :: Python :: 3
Classifier: Programming Language :: Python :: 3.8
Classifier: Programming Language :: Python :: 3.9
Classifier: Programming Language :: Python :: 3.10
Classifier: Topic :: Scientific/Engineering
Requires-Python: >=3.8
License-File: LICENSE
License-File: AUTHORS.rst
Requires-Dist: xrft (>=0.3.0)
Requires-Dist: xarray (>=0.19.0)
Requires-Dist: pandas (>=1.3.3)
Requires-Dist: numpy (>=1.20.3)
Requires-Dist: netCDF4 (>=1.5)
Requires-Dist: matplotlib (>=3.4.3)
Requires-Dist: click (>=8.1.2)
Requires-Dist: gdown (~=4.5.1)
Provides-Extra: dev
Requires-Dist: sphinx-rtd-theme (==0.4.3) ; extra == 'dev'
Provides-Extra: plots
Requires-Dist: matplotlib (>=3.4.3) ; extra == 'plots'
Provides-Extra: test
Requires-Dist: pytest ; extra == 'test'
Requires-Dist: gdown (~=4.5.1) ; extra == 'test'
